aicompleter/__init__.py
aicompleter/__main__.py
aicompleter/common.py
aicompleter/config.py
aicompleter/events.py
aicompleter/handler.py
aicompleter/language.py
aicompleter/layer.py
aicompleter/log.py
aicompleter/namespace.py
aicompleter/ai/__init__.py
aicompleter/ai/ai.py
aicompleter/ai/interface.py
aicompleter/ai/token.py
aicompleter/ai/agent/__init__.py
aicompleter/ai/agent/agent.py
aicompleter/ai/agent/agentf.py
aicompleter/ai/agent/interface.py
aicompleter/ai/agent/reagent.py
aicompleter/ai/prompts/__init__.py
aicompleter/ai/prompts/base.py
aicompleter/error/__init__.py
aicompleter/error/aigenerate.py
aicompleter/error/base.py
aicompleter/error/special.py
aicompleter/implements/__init__.py
aicompleter/implements/authority.py
aicompleter/implements/console.py
aicompleter/implements/searcher.py
aicompleter/implements/logical/__init__.py
aicompleter/implements/logical/cmd_translator.py
aicompleter/implements/logical/subexecutor.py
aicompleter/implements/logical/summarizer.py
aicompleter/implements/logical/taskcompleter.py
aicompleter/implements/logical/taskcompleter_.py
aicompleter/implements/logical/webanalyse.py
aicompleter/implements/system/__init__.py
aicompleter/implements/system/downloader.py
aicompleter/implements/system/file.py
aicompleter/implements/system/pythonc.py
aicompleter/implements/system/shell.py
aicompleter/implements/system/workspace.py
aicompleter/interface/__init__.py
aicompleter/interface/base.py
aicompleter/interface/command.py
aicompleter/memory/__init__.py
aicompleter/memory/base.py
aicompleter/memory/faissimp.py
aicompleter/memory/jsonmem.py
aicompleter/memory/keyword.py
aicompleter/session/__init__.py
aicompleter/session/base.py
aicompleter/utils/__init__.py
aicompleter/utils/aio.py
aicompleter/utils/endict.py
aicompleter/utils/etype.py
aicompleter/utils/launch.py
aicompleter/utils/special.py
aicompleter/utils/storage.py
aicompleter/utils/text.py
aicompleter/utils/typeval.py
aicompleter-0.0.1rc5.dist-info/LICENSE
aicompleter-0.0.1rc5.dist-info/METADATA
aicompleter-0.0.1rc5.dist-info/WHEEL
aicompleter-0.0.1rc5.dist-info/top_level.txt
aicompleter-0.0.1rc5.dist-info/RECORD
