Metadata-Version: 2.1
Name: aicompleter
Version: 0.0.1rc5
Summary: Interactive AI program framework for Python
Author: Li Yan
Author-email: liyanesmail@gmail.com
License: GNU General Public License v3
Project-URL: GitHub: issues, https://github.com/AI-Completer/AI-Completer/issues
Project-URL: GitHub: repo, https://github.com/AI-Completer/AI-Completer
Classifier: Development Status :: 4 - Beta
Classifier: Framework :: AsyncIO
Classifier: License :: OSI Approved :: GNU General Public License v3 (GPLv3)
Classifier: Operating System :: POSIX
Classifier: Operating System :: MacOS :: MacOS X
Classifier: Operating System :: Microsoft :: Windows
Classifier: Programming Language :: Python
Classifier: Programming Language :: Python :: 3
Classifier: Programming Language :: Python :: 3.11
Requires-Python: >=3.11
License-File: LICENSE
Requires-Dist: aiohttp
Requires-Dist: colorama
Requires-Dist: tiktoken
Requires-Dist: shutils
Requires-Dist: attrs
Requires-Dist: paramiko
Requires-Dist: trafilatura
Requires-Dist: EdgeGPT
Requires-Dist: pandas
Provides-Extra: full
Requires-Dist: sentence-transformers ; extra == 'full'
Requires-Dist: pytorch ; extra == 'full'
Requires-Dist: keybert ; extra == 'full'
Requires-Dist: pyreadline3 ; extra == 'full'
